furiosa/serving/__init__.py
furiosa/serving/application.py
furiosa/serving/git_version.txt
furiosa/serving/model.py
furiosa/serving/py.typed
furiosa/serving/telemetry.py
furiosa/serving/apps/__init__.py
furiosa/serving/apps/health.py
furiosa/serving/apps/model.py
furiosa/serving/apps/repository.py
furiosa/serving/processors/__init__.py
furiosa/serving/processors/imagenet.py
furiosa_serving-0.10.2.dist-info/WHEEL
furiosa_serving-0.10.2.dist-info/METADATA
furiosa_serving-0.10.2.dist-info/RECORD
