Metadata-Version: 2.1
Name: furiosa-serving
Version: 0.10.2
Summary: Furiosa serving framework, easy to use inference server.
Author-email: "FurioaAI, Inc." <pkg@furiosa.ai>
Requires-Python: ~=3.8
Classifier: Development Status :: 4 - Beta
Classifier: Environment :: Console
Classifier: Environment :: Web Environment
Classifier: Intended Audience :: Developers
Classifier: Intended Audience :: System Administrators
Classifier: License :: OSI Approved :: Apache Software License
Classifier: Programming Language :: Python :: 3
Classifier: Programming Language :: Python :: 3.8
Classifier: Programming Language :: Python :: 3.9
Classifier: Programming Language :: Python :: 3.10
Classifier: Topic :: Software Development :: Libraries :: Python Modules
Classifier: Topic :: Scientific/Engineering :: Artificial Intelligence
Requires-Dist: furiosa-server == 0.10.*
Requires-Dist: Pillow
Requires-Dist: python-multipart
Requires-Dist: httpx
Requires-Dist: prometheus-client
Requires-Dist: opentelemetry-instrumentation-fastapi
Requires-Dist: opentelemetry-instrumentation-logging
Requires-Dist: opentelemetry-exporter-otlp
Requires-Dist: opentelemetry-api
Requires-Dist: opentelemetry-sdk
Requires-Dist: furiosa-server[openvino] == 0.10.* ; extra == "openvino"
Requires-Dist: transformers ; extra == "openvino"
Requires-Dist: mypy ; extra == "test"
Requires-Dist: pytest ; extra == "test"
Requires-Dist: pytest-asyncio ~= 0.17.2 ; extra == "test"
Requires-Dist: pytest-cov ; extra == "test"
Requires-Dist: ruff ; extra == "test"
Requires-Dist: types-Pillow ; extra == "test"
Project-URL: Bug Tracker, https://github.com/furiosa-ai/furiosa-sdk/issues
Project-URL: Documentation, https://furiosa-ai.github.io/docs
Project-URL: Home, https://furiosa.ai
Project-URL: Source Code, https://github.com/furiosa-ai/furiosa-sdk
Provides-Extra: openvino
Provides-Extra: test
